{
  "A_prox_required": {
    "Full (prox*mag)": {
      "ablation_mode": null,
      "seeds": [
        {
          "config": {
            "window_size": 50,
            "min_support": 3,
            "max_length": 2,
            "change_method": "threshold_crossing",
            "sigma": null,
            "min_magnitude": 0.0,
            "min_relative_change": 0.0,
            "global_correction": true,
            "n_permutations": 5000,
            "alpha": 0.1,
            "seed": 0
          },
          "n_transactions": 5000,
          "n_patterns": 356,
          "n_change_points_total": 0,
          "n_significant": 1,
          "precision": 1.0,
          "recall": 1.0,
          "f1": 1.0,
          "tp": 1,
          "fp": 0,
          "fn": 0,
          "time_phase1_ms": 863.1084589869715,
          "time_support_series_ms": 0.0,
          "time_attribution_ms": 86.69716602889821,
          "time_total_ms": 949.8056250158697,
          "significant_attributions": [
            {
              "pattern": [
                5,
                15
              ],
              "change_time": 1249,
              "change_direction": "down",
              "change_magnitude": 5.199999999999999,
              "event_name": "Sale",
              "event_start": 750,
              "event_end": 1250,
              "proximity": 0.9801986733067553,
              "attribution_score": 7.448295443593761,
              "p_value": 0.0065986802639472104,
              "adjusted_p_value": 0.01979604079184163
            }
          ],
          "true_positive_pairs": [
            {
              "pattern": [
                5,
                15
              ],
              "event_id": "E1"
            }
          ],
          "false_positive_pairs": [],
          "false_negative_pairs": [],
          "false_attribution_rate": 1.0,
          "n_falsely_attributed": 1
        },
        {
          "config": {
            "window_size": 50,
            "min_support": 3,
            "max_length": 2,
            "change_method": "threshold_crossing",
            "sigma": null,
            "min_magnitude": 0.0,
            "min_relative_change": 0.0,
            "global_correction": true,
            "n_permutations": 5000,
            "alpha": 0.1,
            "seed": 1
          },
          "n_transactions": 5000,
          "n_patterns": 338,
          "n_change_points_total": 0,
          "n_significant": 1,
          "precision": 1.0,
          "recall": 1.0,
          "f1": 1.0,
          "tp": 1,
          "fp": 0,
          "fn": 0,
          "time_phase1_ms": 839.3405419774354,
          "time_support_series_ms": 0.0,
          "time_attribution_ms": 100.72412498993799,
          "time_total_ms": 940.0646669673733,
          "significant_attributions": [
            {
              "pattern": [
                5,
                15
              ],
              "change_time": 1249,
              "change_direction": "down",
              "change_magnitude": 5.75,
              "event_name": "Sale",
              "event_start": 750,
              "event_end": 1250,
              "proximity": 0.9801986733067553,
              "attribution_score": 9.331629413129491,
              "p_value": 0.0061987602479504095,
              "adjusted_p_value": 0.030993801239752046
            }
          ],
          "true_positive_pairs": [
            {
              "pattern": [
                5,
                15
              ],
              "event_id": "E1"
            }
          ],
          "false_positive_pairs": [],
          "false_negative_pairs": [],
          "false_attribution_rate": 1.0,
          "n_falsely_attributed": 1
        },
        {
          "config": {
            "window_size": 50,
            "min_support": 3,
            "max_length": 2,
            "change_method": "threshold_crossing",
            "sigma": null,
            "min_magnitude": 0.0,
            "min_relative_change": 0.0,
            "global_correction": true,
            "n_permutations": 5000,
            "alpha": 0.1,
            "seed": 2
          },
          "n_transactions": 5000,
          "n_patterns": 355,
          "n_change_points_total": 0,
          "n_significant": 1,
          "precision": 1.0,
          "recall": 1.0,
          "f1": 1.0,
          "tp": 1,
          "fp": 0,
          "fn": 0,
          "time_phase1_ms": 842.6507499534637,
          "time_support_series_ms": 0.0,
          "time_attribution_ms": 45.83845799788833,
          "time_total_ms": 888.489207951352,
          "significant_attributions": [
            {
              "pattern": [
                5,
                15
              ],
              "change_time": 1244,
              "change_direction": "down",
              "change_magnitude": 4.8,
              "event_name": "Sale",
              "event_start": 750,
              "event_end": 1250,
              "proximity": 0.8869204367171575,
              "attribution_score": 7.518458211174165,
              "p_value": 0.025994801039792043,
              "adjusted_p_value": 0.025994801039792043
            }
          ],
          "true_positive_pairs": [
            {
              "pattern": [
                5,
                15
              ],
              "event_id": "E1"
            }
          ],
          "false_positive_pairs": [],
          "false_negative_pairs": [],
          "false_attribution_rate": 1.0,
          "n_falsely_attributed": 1
        },
        {
          "config": {
            "window_size": 50,
            "min_support": 3,
            "max_length": 2,
            "change_method": "threshold_crossing",
            "sigma": null,
            "min_magnitude": 0.0,
            "min_relative_change": 0.0,
            "global_correction": true,
            "n_permutations": 5000,
            "alpha": 0.1,
            "seed": 3
          },
          "n_transactions": 5000,
          "n_patterns": 330,
          "n_change_points_total": 0,
          "n_significant": 1,
          "precision": 1.0,
          "recall": 1.0,
          "f1": 1.0,
          "tp": 1,
          "fp": 0,
          "fn": 0,
          "time_phase1_ms": 834.6105410018936,
          "time_support_series_ms": 0.0,
          "time_attribution_ms": 127.09312496008351,
          "time_total_ms": 961.7036659619771,
          "significant_attributions": [
            {
              "pattern": [
                5,
                15
              ],
              "change_time": 1249,
              "change_direction": "down",
              "change_magnitude": 8.0,
              "event_name": "Sale",
              "event_start": 750,
              "event_end": 1250,
              "proximity": 0.9801986733067553,
              "attribution_score": 9.201477535255643,
              "p_value": 0.0001999600079984003,
              "adjusted_p_value": 0.0011997600479904018
            }
          ],
          "true_positive_pairs": [
            {
              "pattern": [
                5,
                15
              ],
              "event_id": "E1"
            }
          ],
          "false_positive_pairs": [],
          "false_negative_pairs": [],
          "false_attribution_rate": 1.0,
          "n_falsely_attributed": 1
        },
        {
          "config": {
            "window_size": 50,
            "min_support": 3,
            "max_length": 2,
            "change_method": "threshold_crossing",
            "sigma": null,
            "min_magnitude": 0.0,
            "min_relative_change": 0.0,
            "global_correction": true,
            "n_permutations": 5000,
            "alpha": 0.1,
            "seed": 4
          },
          "n_transactions": 5000,
          "n_patterns": 359,
          "n_change_points_total": 0,
          "n_significant": 1,
          "precision": 1.0,
          "recall": 1.0,
          "f1": 1.0,
          "tp": 1,
          "fp": 0,
          "fn": 0,
          "time_phase1_ms": 846.4595419936813,
          "time_support_series_ms": 0.0,
          "time_attribution_ms": 93.67291699163616,
          "time_total_ms": 940.1324589853175,
          "significant_attributions": [
            {
              "pattern": [
                5,
                15
              ],
              "change_time": 1247,
              "change_direction": "down",
              "change_magnitude": 6.15,
              "event_name": "Sale",
              "event_start": 750,
              "event_end": 1250,
              "proximity": 0.9417645335842487,
              "attribution_score": 8.556525567779204,
              "p_value": 0.009198160367926415,
              "adjusted_p_value": 0.03679264147170566
            }
          ],
          "true_positive_pairs": [
            {
              "pattern": [
                5,
                15
              ],
              "event_id": "E1"
            }
          ],
          "false_positive_pairs": [],
          "false_negative_pairs": [],
          "false_attribution_rate": 1.0,
          "n_falsely_attributed": 1
        }
      ],
      "avg_precision": 1.0,
      "avg_recall": 1.0,
      "avg_f1": 1.0,
      "avg_false_attribution_rate": 1.0
    },
    "No proximity (mag only)": {
      "ablation_mode": "no_prox",
      "seeds": [
        {
          "config": {
            "window_size": 50,
            "min_support": 3,
            "max_length": 2,
            "change_method": "threshold_crossing",
            "sigma": null,
            "min_magnitude": 0.0,
            "min_relative_change": 0.0,
            "global_correction": true,
            "n_permutations": 5000,
            "alpha": 0.1,
            "seed": 0
          },
          "n_transactions": 5000,
          "n_patterns": 356,
          "n_change_points_total": 0,
          "n_significant": 0,
          "precision": 0.0,
          "recall": 0.0,
          "f1": 0.0,
          "tp": 0,
          "fp": 0,
          "fn": 1,
          "time_phase1_ms": 845.2293330337852,
          "time_support_series_ms": 0.0,
          "time_attribution_ms": 170.3434999799356,
          "time_total_ms": 1015.5728330137208,
          "significant_attributions": [],
          "true_positive_pairs": [],
          "false_positive_pairs": [],
          "false_negative_pairs": [
            {
              "pattern": [
                5,
                15
              ],
              "event_id": "E1"
            }
          ],
          "false_attribution_rate": 0.0,
          "n_falsely_attributed": 0
        },
        {
          "config": {
            "window_size": 50,
            "min_support": 3,
            "max_length": 2,
            "change_method": "threshold_crossing",
            "sigma": null,
            "min_magnitude": 0.0,
            "min_relative_change": 0.0,
            "global_correction": true,
            "n_permutations": 5000,
            "alpha": 0.1,
            "seed": 1
          },
          "n_transactions": 5000,
          "n_patterns": 338,
          "n_change_points_total": 0,
          "n_significant": 0,
          "precision": 0.0,
          "recall": 0.0,
          "f1": 0.0,
          "tp": 0,
          "fp": 0,
          "fn": 1,
          "time_phase1_ms": 842.5237500341609,
          "time_support_series_ms": 0.0,
          "time_attribution_ms": 223.66591601166874,
          "time_total_ms": 1066.1896660458297,
          "significant_attributions": [],
          "true_positive_pairs": [],
          "false_positive_pairs": [],
          "false_negative_pairs": [
            {
              "pattern": [
                5,
                15
              ],
              "event_id": "E1"
            }
          ],
          "false_attribution_rate": 0.0,
          "n_falsely_attributed": 0
        },
        {
          "config": {
            "window_size": 50,
            "min_support": 3,
            "max_length": 2,
            "change_method": "threshold_crossing",
            "sigma": null,
            "min_magnitude": 0.0,
            "min_relative_change": 0.0,
            "global_correction": true,
            "n_permutations": 5000,
            "alpha": 0.1,
            "seed": 2
          },
          "n_transactions": 5000,
          "n_patterns": 355,
          "n_change_points_total": 0,
          "n_significant": 0,
          "precision": 0.0,
          "recall": 0.0,
          "f1": 0.0,
          "tp": 0,
          "fp": 0,
          "fn": 1,
          "time_phase1_ms": 851.4519589953125,
          "time_support_series_ms": 0.0,
          "time_attribution_ms": 134.2345830053091,
          "time_total_ms": 985.6865420006216,
          "significant_attributions": [],
          "true_positive_pairs": [],
          "false_positive_pairs": [],
          "false_negative_pairs": [
            {
              "pattern": [
                5,
                15
              ],
              "event_id": "E1"
            }
          ],
          "false_attribution_rate": 0.0,
          "n_falsely_attributed": 0
        },
        {
          "config": {
            "window_size": 50,
            "min_support": 3,
            "max_length": 2,
            "change_method": "threshold_crossing",
            "sigma": null,
            "min_magnitude": 0.0,
            "min_relative_change": 0.0,
            "global_correction": true,
            "n_permutations": 5000,
            "alpha": 0.1,
            "seed": 3
          },
          "n_transactions": 5000,
          "n_patterns": 330,
          "n_change_points_total": 0,
          "n_significant": 0,
          "precision": 0.0,
          "recall": 0.0,
          "f1": 0.0,
          "tp": 0,
          "fp": 0,
          "fn": 1,
          "time_phase1_ms": 841.5292089921422,
          "time_support_series_ms": 0.0,
          "time_attribution_ms": 172.1728330012411,
          "time_total_ms": 1013.7020419933833,
          "significant_attributions": [],
          "true_positive_pairs": [],
          "false_positive_pairs": [],
          "false_negative_pairs": [
            {
              "pattern": [
                5,
                15
              ],
              "event_id": "E1"
            }
          ],
          "false_attribution_rate": 0.0,
          "n_falsely_attributed": 0
        },
        {
          "config": {
            "window_size": 50,
            "min_support": 3,
            "max_length": 2,
            "change_method": "threshold_crossing",
            "sigma": null,
            "min_magnitude": 0.0,
            "min_relative_change": 0.0,
            "global_correction": true,
            "n_permutations": 5000,
            "alpha": 0.1,
            "seed": 4
          },
          "n_transactions": 5000,
          "n_patterns": 359,
          "n_change_points_total": 0,
          "n_significant": 0,
          "precision": 0.0,
          "recall": 0.0,
          "f1": 0.0,
          "tp": 0,
          "fp": 0,
          "fn": 1,
          "time_phase1_ms": 854.2499170289375,
          "time_support_series_ms": 0.0,
          "time_attribution_ms": 155.5284169735387,
          "time_total_ms": 1009.7783340024762,
          "significant_attributions": [],
          "true_positive_pairs": [],
          "false_positive_pairs": [],
          "false_negative_pairs": [
            {
              "pattern": [
                5,
                15
              ],
              "event_id": "E1"
            }
          ],
          "false_attribution_rate": 0.0,
          "n_falsely_attributed": 0
        }
      ],
      "avg_precision": 0.0,
      "avg_recall": 0.0,
      "avg_f1": 0.0,
      "avg_false_attribution_rate": 0.0
    },
    "No magnitude (prox only)": {
      "ablation_mode": "no_mag",
      "seeds": [
        {
          "config": {
            "window_size": 50,
            "min_support": 3,
            "max_length": 2,
            "change_method": "threshold_crossing",
            "sigma": null,
            "min_magnitude": 0.0,
            "min_relative_change": 0.0,
            "global_correction": true,
            "n_permutations": 5000,
            "alpha": 0.1,
            "seed": 0
          },
          "n_transactions": 5000,
          "n_patterns": 356,
          "n_change_points_total": 0,
          "n_significant": 1,
          "precision": 0.0,
          "recall": 0.0,
          "f1": 0.0,
          "tp": 0,
          "fp": 1,
          "fn": 1,
          "time_phase1_ms": 854.2401249869727,
          "time_support_series_ms": 0.0,
          "time_attribution_ms": 83.0696250195615,
          "time_total_ms": 937.3097500065342,
          "significant_attributions": [
            {
              "pattern": [
                5,
                166
              ],
              "change_time": 777,
              "change_direction": "down",
              "change_magnitude": 1.0,
              "event_name": "Sale",
              "event_start": 750,
              "event_end": 1250,
              "proximity": 0.5827482523739896,
              "attribution_score": 2.6809826544232487,
              "p_value": 0.033193361327734455,
              "adjusted_p_value": 0.04979004199160168
            }
          ],
          "true_positive_pairs": [],
          "false_positive_pairs": [
            {
              "pattern": [
                5,
                166
              ],
              "event_id": "E1"
            }
          ],
          "false_negative_pairs": [
            {
              "pattern": [
                5,
                15
              ],
              "event_id": "E1"
            }
          ],
          "false_attribution_rate": 0.0,
          "n_falsely_attributed": 0
        },
        {
          "config": {
            "window_size": 50,
            "min_support": 3,
            "max_length": 2,
            "change_method": "threshold_crossing",
            "sigma": null,
            "min_magnitude": 0.0,
            "min_relative_change": 0.0,
            "global_correction": true,
            "n_permutations": 5000,
            "alpha": 0.1,
            "seed": 1
          },
          "n_transactions": 5000,
          "n_patterns": 338,
          "n_change_points_total": 0,
          "n_significant": 1,
          "precision": 1.0,
          "recall": 1.0,
          "f1": 1.0,
          "tp": 1,
          "fp": 0,
          "fn": 0,
          "time_phase1_ms": 870.2413749997504,
          "time_support_series_ms": 0.0,
          "time_attribution_ms": 63.046000024769455,
          "time_total_ms": 933.2873750245199,
          "significant_attributions": [
            {
              "pattern": [
                5,
                15
              ],
              "change_time": 1249,
              "change_direction": "down",
              "change_magnitude": 5.75,
              "event_name": "Sale",
              "event_start": 750,
              "event_end": 1250,
              "proximity": 0.9801986733067553,
              "attribution_score": 1.4970500077984545,
              "p_value": 0.001799640071985603,
              "adjusted_p_value": 0.005398920215956809
            }
          ],
          "true_positive_pairs": [
            {
              "pattern": [
                5,
                15
              ],
              "event_id": "E1"
            }
          ],
          "false_positive_pairs": [],
          "false_negative_pairs": [],
          "false_attribution_rate": 1.0,
          "n_falsely_attributed": 1
        },
        {
          "config": {
            "window_size": 50,
            "min_support": 3,
            "max_length": 2,
            "change_method": "threshold_crossing",
            "sigma": null,
            "min_magnitude": 0.0,
            "min_relative_change": 0.0,
            "global_correction": true,
            "n_permutations": 5000,
            "alpha": 0.1,
            "seed": 2
          },
          "n_transactions": 5000,
          "n_patterns": 355,
          "n_change_points_total": 0,
          "n_significant": 1,
          "precision": 1.0,
          "recall": 1.0,
          "f1": 1.0,
          "tp": 1,
          "fp": 0,
          "fn": 0,
          "time_phase1_ms": 852.6460000430234,
          "time_support_series_ms": 0.0,
          "time_attribution_ms": 43.91329095233232,
          "time_total_ms": 896.5592909953557,
          "significant_attributions": [
            {
              "pattern": [
                5,
                15
              ],
              "change_time": 1244,
              "change_direction": "down",
              "change_magnitude": 4.8,
              "event_name": "Sale",
              "event_start": 750,
              "event_end": 1250,
              "proximity": 0.8869204367171575,
              "attribution_score": 1.3736726926771292,
              "p_value": 0.007398520295940812,
              "adjusted_p_value": 0.007398520295940812
            }
          ],
          "true_positive_pairs": [
            {
              "pattern": [
                5,
                15
              ],
              "event_id": "E1"
            }
          ],
          "false_positive_pairs": [],
          "false_negative_pairs": [],
          "false_attribution_rate": 1.0,
          "n_falsely_attributed": 1
        },
        {
          "config": {
            "window_size": 50,
            "min_support": 3,
            "max_length": 2,
            "change_method": "threshold_crossing",
            "sigma": null,
            "min_magnitude": 0.0,
            "min_relative_change": 0.0,
            "global_correction": true,
            "n_permutations": 5000,
            "alpha": 0.1,
            "seed": 3
          },
          "n_transactions": 5000,
          "n_patterns": 330,
          "n_change_points_total": 0,
          "n_significant": 1,
          "precision": 1.0,
          "recall": 1.0,
          "f1": 1.0,
          "tp": 1,
          "fp": 0,
          "fn": 0,
          "time_phase1_ms": 837.9447080078535,
          "time_support_series_ms": 0.0,
          "time_attribution_ms": 118.55458404170349,
          "time_total_ms": 956.499292049557,
          "significant_attributions": [
            {
              "pattern": [
                5,
                15
              ],
              "change_time": 1249,
              "change_direction": "down",
              "change_magnitude": 8.0,
              "event_name": "Sale",
              "event_start": 750,
              "event_end": 1250,
              "proximity": 0.9801986733067553,
              "attribution_score": 1.411909196735835,
              "p_value": 0.0013997200559888023,
              "adjusted_p_value": 0.008398320335932814
            }
          ],
          "true_positive_pairs": [
            {
              "pattern": [
                5,
                15
              ],
              "event_id": "E1"
            }
          ],
          "false_positive_pairs": [],
          "false_negative_pairs": [],
          "false_attribution_rate": 1.0,
          "n_falsely_attributed": 1
        },
        {
          "config": {
            "window_size": 50,
            "min_support": 3,
            "max_length": 2,
            "change_method": "threshold_crossing",
            "sigma": null,
            "min_magnitude": 0.0,
            "min_relative_change": 0.0,
            "global_correction": true,
            "n_permutations": 5000,
            "alpha": 0.1,
            "seed": 4
          },
          "n_transactions": 5000,
          "n_patterns": 359,
          "n_change_points_total": 0,
          "n_significant": 0,
          "precision": 0.0,
          "recall": 0.0,
          "f1": 0.0,
          "tp": 0,
          "fp": 0,
          "fn": 1,
          "time_phase1_ms": 895.078333967831,
          "time_support_series_ms": 0.0,
          "time_attribution_ms": 89.85829103039578,
          "time_total_ms": 984.9366249982268,
          "significant_attributions": [],
          "true_positive_pairs": [],
          "false_positive_pairs": [],
          "false_negative_pairs": [
            {
              "pattern": [
                5,
                15
              ],
              "event_id": "E1"
            }
          ],
          "false_attribution_rate": 0.0,
          "n_falsely_attributed": 0
        }
      ],
      "avg_precision": 0.6,
      "avg_recall": 0.6,
      "avg_f1": 0.6,
      "avg_false_attribution_rate": 0.6
    }
  },
  "B_mag_required": {
    "Full (prox*mag)": {
      "ablation_mode": null,
      "seeds": [
        {
          "config": {
            "window_size": 50,
            "min_support": 3,
            "max_length": 2,
            "change_method": "threshold_crossing",
            "sigma": null,
            "min_magnitude": 0.0,
            "min_relative_change": 0.0,
            "global_correction": true,
            "n_permutations": 5000,
            "alpha": 0.1,
            "seed": 0
          },
          "n_transactions": 5000,
          "n_patterns": 328,
          "n_change_points_total": 0,
          "n_significant": 2,
          "precision": 1.0,
          "recall": 1.0,
          "f1": 1.0,
          "tp": 2,
          "fp": 0,
          "fn": 0,
          "time_phase1_ms": 873.2252089539543,
          "time_support_series_ms": 0.0,
          "time_attribution_ms": 237.3024999978952,
          "time_total_ms": 1110.5277089518495,
          "significant_attributions": [
            {
              "pattern": [
                5,
                15
              ],
              "change_time": 1198,
              "change_direction": "down",
              "change_magnitude": 6.1,
              "event_name": "BigSale",
              "event_start": 800,
              "event_end": 1200,
              "proximity": 0.9607894391523232,
              "attribution_score": 8.525524380674108,
              "p_value": 0.00639872025594881,
              "adjusted_p_value": 0.033593281343731254
            },
            {
              "pattern": [
                5,
                15
              ],
              "change_time": 2507,
              "change_direction": "down",
              "change_magnitude": 2.75,
              "event_name": "SmallPromo",
              "event_start": 2500,
              "event_end": 2900,
              "proximity": 0.8693582353988059,
              "attribution_score": 6.019468355252775,
              "p_value": 0.027994401119776045,
              "adjusted_p_value": 0.033593281343731254
            }
          ],
          "true_positive_pairs": [
            {
              "pattern": [
                5,
                15
              ],
              "event_id": "E2"
            },
            {
              "pattern": [
                5,
                15
              ],
              "event_id": "E1"
            }
          ],
          "false_positive_pairs": [],
          "false_negative_pairs": [],
          "false_attribution_rate": 0.0,
          "n_falsely_attributed": 0
        },
        {
          "config": {
            "window_size": 50,
            "min_support": 3,
            "max_length": 2,
            "change_method": "threshold_crossing",
            "sigma": null,
            "min_magnitude": 0.0,
            "min_relative_change": 0.0,
            "global_correction": true,
            "n_permutations": 5000,
            "alpha": 0.1,
            "seed": 1
          },
          "n_transactions": 5000,
          "n_patterns": 319,
          "n_change_points_total": 0,
          "n_significant": 1,
          "precision": 1.0,
          "recall": 0.5,
          "f1": 0.6666666666666666,
          "tp": 1,
          "fp": 0,
          "fn": 1,
          "time_phase1_ms": 841.503375035245,
          "time_support_series_ms": 0.0,
          "time_attribution_ms": 165.40183394681662,
          "time_total_ms": 1006.9052089820616,
          "significant_attributions": [
            {
              "pattern": [
                5,
                15
              ],
              "change_time": 1198,
              "change_direction": "down",
              "change_magnitude": 6.449999999999999,
              "event_name": "BigSale",
              "event_start": 800,
              "event_end": 1200,
              "proximity": 0.9607894391523232,
              "attribution_score": 9.086354930395212,
              "p_value": 0.004599080183963208,
              "adjusted_p_value": 0.03679264147170566
            }
          ],
          "true_positive_pairs": [
            {
              "pattern": [
                5,
                15
              ],
              "event_id": "E1"
            }
          ],
          "false_positive_pairs": [],
          "false_negative_pairs": [
            {
              "pattern": [
                5,
                15
              ],
              "event_id": "E2"
            }
          ],
          "false_attribution_rate": 0.0,
          "n_falsely_attributed": 0
        },
        {
          "config": {
            "window_size": 50,
            "min_support": 3,
            "max_length": 2,
            "change_method": "threshold_crossing",
            "sigma": null,
            "min_magnitude": 0.0,
            "min_relative_change": 0.0,
            "global_correction": true,
            "n_permutations": 5000,
            "alpha": 0.1,
            "seed": 2
          },
          "n_transactions": 5000,
          "n_patterns": 337,
          "n_change_points_total": 0,
          "n_significant": 1,
          "precision": 1.0,
          "recall": 0.5,
          "f1": 0.6666666666666666,
          "tp": 1,
          "fp": 0,
          "fn": 1,
          "time_phase1_ms": 857.309749990236,
          "time_support_series_ms": 0.0,
          "time_attribution_ms": 246.0731250466779,
          "time_total_ms": 1103.382875036914,
          "significant_attributions": [
            {
              "pattern": [
                5,
                15
              ],
              "change_time": 1201,
              "change_direction": "down",
              "change_magnitude": 4.85,
              "event_name": "BigSale",
              "event_start": 800,
              "event_end": 1200,
              "proximity": 0.9801986733067553,
              "attribution_score": 7.155954598186721,
              "p_value": 0.0057988402319536095,
              "adjusted_p_value": 0.06958608278344332
            }
          ],
          "true_positive_pairs": [
            {
              "pattern": [
                5,
                15
              ],
              "event_id": "E1"
            }
          ],
          "false_positive_pairs": [],
          "false_negative_pairs": [
            {
              "pattern": [
                5,
                15
              ],
              "event_id": "E2"
            }
          ],
          "false_attribution_rate": 0.0,
          "n_falsely_attributed": 0
        },
        {
          "config": {
            "window_size": 50,
            "min_support": 3,
            "max_length": 2,
            "change_method": "threshold_crossing",
            "sigma": null,
            "min_magnitude": 0.0,
            "min_relative_change": 0.0,
            "global_correction": true,
            "n_permutations": 5000,
            "alpha": 0.1,
            "seed": 3
          },
          "n_transactions": 5000,
          "n_patterns": 279,
          "n_change_points_total": 0,
          "n_significant": 1,
          "precision": 1.0,
          "recall": 0.5,
          "f1": 0.6666666666666666,
          "tp": 1,
          "fp": 0,
          "fn": 1,
          "time_phase1_ms": 836.7909590015188,
          "time_support_series_ms": 0.0,
          "time_attribution_ms": 199.8565829708241,
          "time_total_ms": 1036.6475419723429,
          "significant_attributions": [
            {
              "pattern": [
                5,
                15
              ],
              "change_time": 1196,
              "change_direction": "down",
              "change_magnitude": 9.65,
              "event_name": "BigSale",
              "event_start": 800,
              "event_end": 1200,
              "proximity": 0.9231163463866358,
              "attribution_score": 11.642467590140683,
              "p_value": 0.0021995600879824036,
              "adjusted_p_value": 0.01759648070385923
            }
          ],
          "true_positive_pairs": [
            {
              "pattern": [
                5,
                15
              ],
              "event_id": "E1"
            }
          ],
          "false_positive_pairs": [],
          "false_negative_pairs": [
            {
              "pattern": [
                5,
                15
              ],
              "event_id": "E2"
            }
          ],
          "false_attribution_rate": 0.0,
          "n_falsely_attributed": 0
        },
        {
          "config": {
            "window_size": 50,
            "min_support": 3,
            "max_length": 2,
            "change_method": "threshold_crossing",
            "sigma": null,
            "min_magnitude": 0.0,
            "min_relative_change": 0.0,
            "global_correction": true,
            "n_permutations": 5000,
            "alpha": 0.1,
            "seed": 4
          },
          "n_transactions": 5000,
          "n_patterns": 351,
          "n_change_points_total": 0,
          "n_significant": 2,
          "precision": 1.0,
          "recall": 1.0,
          "f1": 1.0,
          "tp": 2,
          "fp": 0,
          "fn": 0,
          "time_phase1_ms": 848.786290967837,
          "time_support_series_ms": 0.0,
          "time_attribution_ms": 147.80754200182855,
          "time_total_ms": 996.5938329696655,
          "significant_attributions": [
            {
              "pattern": [
                5,
                15
              ],
              "change_time": 1194,
              "change_direction": "down",
              "change_magnitude": 8.2,
              "event_name": "BigSale",
              "event_start": 800,
              "event_end": 1200,
              "proximity": 0.8869204367171575,
              "attribution_score": 10.062380868672289,
              "p_value": 0.011197760447910418,
              "adjusted_p_value": 0.04479104179164167
            },
            {
              "pattern": [
                5,
                15
              ],
              "change_time": 2889,
              "change_direction": "down",
              "change_magnitude": 3.1999999999999997,
              "event_name": "SmallPromo",
              "event_start": 2500,
              "event_end": 2900,
              "proximity": 0.8025187979624785,
              "attribution_score": 5.465862697659927,
              "p_value": 0.04319136172765447,
              "adjusted_p_value": 0.07518496300739852
            }
          ],
          "true_positive_pairs": [
            {
              "pattern": [
                5,
                15
              ],
              "event_id": "E2"
            },
            {
              "pattern": [
                5,
                15
              ],
              "event_id": "E1"
            }
          ],
          "false_positive_pairs": [],
          "false_negative_pairs": [],
          "false_attribution_rate": 0.0,
          "n_falsely_attributed": 0
        }
      ],
      "avg_precision": 1.0,
      "avg_recall": 0.7,
      "avg_f1": 0.8,
      "avg_false_attribution_rate": 0.0
    },
    "No proximity (mag only)": {
      "ablation_mode": "no_prox",
      "seeds": [
        {
          "config": {
            "window_size": 50,
            "min_support": 3,
            "max_length": 2,
            "change_method": "threshold_crossing",
            "sigma": null,
            "min_magnitude": 0.0,
            "min_relative_change": 0.0,
            "global_correction": true,
            "n_permutations": 5000,
            "alpha": 0.1,
            "seed": 0
          },
          "n_transactions": 5000,
          "n_patterns": 328,
          "n_change_points_total": 0,
          "n_significant": 0,
          "precision": 0.0,
          "recall": 0.0,
          "f1": 0.0,
          "tp": 0,
          "fp": 0,
          "fn": 2,
          "time_phase1_ms": 850.505415990483,
          "time_support_series_ms": 0.0,
          "time_attribution_ms": 456.20595902437344,
          "time_total_ms": 1306.7113750148565,
          "significant_attributions": [],
          "true_positive_pairs": [],
          "false_positive_pairs": [],
          "false_negative_pairs": [
            {
              "pattern": [
                5,
                15
              ],
              "event_id": "E2"
            },
            {
              "pattern": [
                5,
                15
              ],
              "event_id": "E1"
            }
          ],
          "false_attribution_rate": 0.0,
          "n_falsely_attributed": 0
        },
        {
          "config": {
            "window_size": 50,
            "min_support": 3,
            "max_length": 2,
            "change_method": "threshold_crossing",
            "sigma": null,
            "min_magnitude": 0.0,
            "min_relative_change": 0.0,
            "global_correction": true,
            "n_permutations": 5000,
            "alpha": 0.1,
            "seed": 1
          },
          "n_transactions": 5000,
          "n_patterns": 319,
          "n_change_points_total": 0,
          "n_significant": 0,
          "precision": 0.0,
          "recall": 0.0,
          "f1": 0.0,
          "tp": 0,
          "fp": 0,
          "fn": 2,
          "time_phase1_ms": 896.1748330038972,
          "time_support_series_ms": 0.0,
          "time_attribution_ms": 315.70758298039436,
          "time_total_ms": 1211.8824159842916,
          "significant_attributions": [],
          "true_positive_pairs": [],
          "false_positive_pairs": [],
          "false_negative_pairs": [
            {
              "pattern": [
                5,
                15
              ],
              "event_id": "E2"
            },
            {
              "pattern": [
                5,
                15
              ],
              "event_id": "E1"
            }
          ],
          "false_attribution_rate": 0.0,
          "n_falsely_attributed": 0
        },
        {
          "config": {
            "window_size": 50,
            "min_support": 3,
            "max_length": 2,
            "change_method": "threshold_crossing",
            "sigma": null,
            "min_magnitude": 0.0,
            "min_relative_change": 0.0,
            "global_correction": true,
            "n_permutations": 5000,
            "alpha": 0.1,
            "seed": 2
          },
          "n_transactions": 5000,
          "n_patterns": 337,
          "n_change_points_total": 0,
          "n_significant": 0,
          "precision": 0.0,
          "recall": 0.0,
          "f1": 0.0,
          "tp": 0,
          "fp": 0,
          "fn": 2,
          "time_phase1_ms": 875.4206249723211,
          "time_support_series_ms": 0.0,
          "time_attribution_ms": 360.5481249978766,
          "time_total_ms": 1235.9687499701977,
          "significant_attributions": [],
          "true_positive_pairs": [],
          "false_positive_pairs": [],
          "false_negative_pairs": [
            {
              "pattern": [
                5,
                15
              ],
              "event_id": "E2"
            },
            {
              "pattern": [
                5,
                15
              ],
              "event_id": "E1"
            }
          ],
          "false_attribution_rate": 0.0,
          "n_falsely_attributed": 0
        },
        {
          "config": {
            "window_size": 50,
            "min_support": 3,
            "max_length": 2,
            "change_method": "threshold_crossing",
            "sigma": null,
            "min_magnitude": 0.0,
            "min_relative_change": 0.0,
            "global_correction": true,
            "n_permutations": 5000,
            "alpha": 0.1,
            "seed": 3
          },
          "n_transactions": 5000,
          "n_patterns": 279,
          "n_change_points_total": 0,
          "n_significant": 0,
          "precision": 0.0,
          "recall": 0.0,
          "f1": 0.0,
          "tp": 0,
          "fp": 0,
          "fn": 2,
          "time_phase1_ms": 854.4745410326868,
          "time_support_series_ms": 0.0,
          "time_attribution_ms": 296.81395896477625,
          "time_total_ms": 1151.288499997463,
          "significant_attributions": [],
          "true_positive_pairs": [],
          "false_positive_pairs": [],
          "false_negative_pairs": [
            {
              "pattern": [
                5,
                15
              ],
              "event_id": "E2"
            },
            {
              "pattern": [
                5,
                15
              ],
              "event_id": "E1"
            }
          ],
          "false_attribution_rate": 0.0,
          "n_falsely_attributed": 0
        },
        {
          "config": {
            "window_size": 50,
            "min_support": 3,
            "max_length": 2,
            "change_method": "threshold_crossing",
            "sigma": null,
            "min_magnitude": 0.0,
            "min_relative_change": 0.0,
            "global_correction": true,
            "n_permutations": 5000,
            "alpha": 0.1,
            "seed": 4
          },
          "n_transactions": 5000,
          "n_patterns": 351,
          "n_change_points_total": 0,
          "n_significant": 0,
          "precision": 0.0,
          "recall": 0.0,
          "f1": 0.0,
          "tp": 0,
          "fp": 0,
          "fn": 2,
          "time_phase1_ms": 884.0793329873122,
          "time_support_series_ms": 0.0,
          "time_attribution_ms": 230.12279201066121,
          "time_total_ms": 1114.2021249979734,
          "significant_attributions": [],
          "true_positive_pairs": [],
          "false_positive_pairs": [],
          "false_negative_pairs": [
            {
              "pattern": [
                5,
                15
              ],
              "event_id": "E2"
            },
            {
              "pattern": [
                5,
                15
              ],
              "event_id": "E1"
            }
          ],
          "false_attribution_rate": 0.0,
          "n_falsely_attributed": 0
        }
      ],
      "avg_precision": 0.0,
      "avg_recall": 0.0,
      "avg_f1": 0.0,
      "avg_false_attribution_rate": 0.0
    },
    "No magnitude (prox only)": {
      "ablation_mode": "no_mag",
      "seeds": [
        {
          "config": {
            "window_size": 50,
            "min_support": 3,
            "max_length": 2,
            "change_method": "threshold_crossing",
            "sigma": null,
            "min_magnitude": 0.0,
            "min_relative_change": 0.0,
            "global_correction": true,
            "n_permutations": 5000,
            "alpha": 0.1,
            "seed": 0
          },
          "n_transactions": 5000,
          "n_patterns": 328,
          "n_change_points_total": 0,
          "n_significant": 2,
          "precision": 0.5,
          "recall": 0.5,
          "f1": 0.5,
          "tp": 1,
          "fp": 1,
          "fn": 1,
          "time_phase1_ms": 870.583624986466,
          "time_support_series_ms": 0.0,
          "time_attribution_ms": 220.13812500517815,
          "time_total_ms": 1090.7217499916442,
          "significant_attributions": [
            {
              "pattern": [
                5,
                15
              ],
              "change_time": 2507,
              "change_direction": "down",
              "change_magnitude": 2.75,
              "event_name": "SmallPromo",
              "event_start": 2500,
              "event_end": 2900,
              "proximity": 0.8693582353988059,
              "attribution_score": 2.347203627137244,
              "p_value": 0.01859628074385123,
              "adjusted_p_value": 0.0635872825434913
            },
            {
              "pattern": [
                15,
                80
              ],
              "change_time": 822,
              "change_direction": "down",
              "change_magnitude": 1.4000000000000004,
              "event_name": "BigSale",
              "event_start": 800,
              "event_end": 1200,
              "proximity": 0.6440364210831414,
              "attribution_score": 2.3109435763753083,
              "p_value": 0.021195760847830435,
              "adjusted_p_value": 0.0635872825434913
            }
          ],
          "true_positive_pairs": [
            {
              "pattern": [
                5,
                15
              ],
              "event_id": "E2"
            }
          ],
          "false_positive_pairs": [
            {
              "pattern": [
                15,
                80
              ],
              "event_id": "E1"
            }
          ],
          "false_negative_pairs": [
            {
              "pattern": [
                5,
                15
              ],
              "event_id": "E1"
            }
          ],
          "false_attribution_rate": 0.0,
          "n_falsely_attributed": 0
        },
        {
          "config": {
            "window_size": 50,
            "min_support": 3,
            "max_length": 2,
            "change_method": "threshold_crossing",
            "sigma": null,
            "min_magnitude": 0.0,
            "min_relative_change": 0.0,
            "global_correction": true,
            "n_permutations": 5000,
            "alpha": 0.1,
            "seed": 1
          },
          "n_transactions": 5000,
          "n_patterns": 319,
          "n_change_points_total": 0,
          "n_significant": 2,
          "precision": 0.5,
          "recall": 0.5,
          "f1": 0.5,
          "tp": 1,
          "fp": 1,
          "fn": 1,
          "time_phase1_ms": 868.5527499765158,
          "time_support_series_ms": 0.0,
          "time_attribution_ms": 108.06337499525398,
          "time_total_ms": 976.6161249717698,
          "significant_attributions": [
            {
              "pattern": [
                15,
                52
              ],
              "change_time": 1200,
              "change_direction": "down",
              "change_magnitude": 1.7499999999999998,
              "event_name": "BigSale",
              "event_start": 800,
              "event_end": 1200,
              "proximity": 1.0,
              "attribution_score": 1.3605949401730784,
              "p_value": 0.04819036192761448,
              "adjusted_p_value": 0.0631873625274945
            },
            {
              "pattern": [
                5,
                15
              ],
              "change_time": 2531,
              "change_direction": "up",
              "change_magnitude": 2.15,
              "event_name": "SmallPromo",
              "event_start": 2500,
              "event_end": 2900,
              "proximity": 0.5379444375946745,
              "attribution_score": 1.0056108646045838,
              "p_value": 0.03479304139172166,
              "adjusted_p_value": 0.0631873625274945
            }
          ],
          "true_positive_pairs": [
            {
              "pattern": [
                5,
                15
              ],
              "event_id": "E2"
            }
          ],
          "false_positive_pairs": [
            {
              "pattern": [
                15,
                52
              ],
              "event_id": "E1"
            }
          ],
          "false_negative_pairs": [
            {
              "pattern": [
                5,
                15
              ],
              "event_id": "E1"
            }
          ],
          "false_attribution_rate": 0.0,
          "n_falsely_attributed": 0
        },
        {
          "config": {
            "window_size": 50,
            "min_support": 3,
            "max_length": 2,
            "change_method": "threshold_crossing",
            "sigma": null,
            "min_magnitude": 0.0,
            "min_relative_change": 0.0,
            "global_correction": true,
            "n_permutations": 5000,
            "alpha": 0.1,
            "seed": 2
          },
          "n_transactions": 5000,
          "n_patterns": 337,
          "n_change_points_total": 0,
          "n_significant": 2,
          "precision": 0.5,
          "recall": 0.5,
          "f1": 0.5,
          "tp": 1,
          "fp": 1,
          "fn": 1,
          "time_phase1_ms": 862.9392920411192,
          "time_support_series_ms": 0.0,
          "time_attribution_ms": 185.7028749655001,
          "time_total_ms": 1048.6421670066193,
          "significant_attributions": [
            {
              "pattern": [
                5,
                15
              ],
              "change_time": 2901,
              "change_direction": "down",
              "change_magnitude": 1.7,
              "event_name": "SmallPromo",
              "event_start": 2500,
              "event_end": 2900,
              "proximity": 0.9801986733067553,
              "attribution_score": 3.369415819918419,
              "p_value": 0.016996600679864027,
              "adjusted_p_value": 0.06798640271945611
            },
            {
              "pattern": [
                5,
                132
              ],
              "change_time": 827,
              "change_direction": "up",
              "change_magnitude": 2.6500000000000004,
              "event_name": "BigSale",
              "event_start": 800,
              "event_end": 1200,
              "proximity": 0.5827482523739896,
              "attribution_score": 0.7180835356106023,
              "p_value": 0.049590081983603276,
              "adjusted_p_value": 0.09918016396720655
            }
          ],
          "true_positive_pairs": [
            {
              "pattern": [
                5,
                15
              ],
              "event_id": "E2"
            }
          ],
          "false_positive_pairs": [
            {
              "pattern": [
                5,
                132
              ],
              "event_id": "E1"
            }
          ],
          "false_negative_pairs": [
            {
              "pattern": [
                5,
                15
              ],
              "event_id": "E1"
            }
          ],
          "false_attribution_rate": 0.0,
          "n_falsely_attributed": 0
        },
        {
          "config": {
            "window_size": 50,
            "min_support": 3,
            "max_length": 2,
            "change_method": "threshold_crossing",
            "sigma": null,
            "min_magnitude": 0.0,
            "min_relative_change": 0.0,
            "global_correction": true,
            "n_permutations": 5000,
            "alpha": 0.1,
            "seed": 3
          },
          "n_transactions": 5000,
          "n_patterns": 279,
          "n_change_points_total": 0,
          "n_significant": 1,
          "precision": 0.0,
          "recall": 0.0,
          "f1": 0.0,
          "tp": 0,
          "fp": 1,
          "fn": 2,
          "time_phase1_ms": 854.2998749762774,
          "time_support_series_ms": 0.0,
          "time_attribution_ms": 175.7742909830995,
          "time_total_ms": 1030.0741659593768,
          "significant_attributions": [
            {
              "pattern": [
                5,
                83
              ],
              "change_time": 799,
              "change_direction": "up",
              "change_magnitude": 1.85,
              "event_name": "BigSale",
              "event_start": 800,
              "event_end": 1200,
              "proximity": 0.9801986733067553,
              "attribution_score": 1.562946925680745,
              "p_value": 0.0011997600479904018,
              "adjusted_p_value": 0.004199160167966407
            }
          ],
          "true_positive_pairs": [],
          "false_positive_pairs": [
            {
              "pattern": [
                5,
                83
              ],
              "event_id": "E1"
            }
          ],
          "false_negative_pairs": [
            {
              "pattern": [
                5,
                15
              ],
              "event_id": "E2"
            },
            {
              "pattern": [
                5,
                15
              ],
              "event_id": "E1"
            }
          ],
          "false_attribution_rate": 0.0,
          "n_falsely_attributed": 0
        },
        {
          "config": {
            "window_size": 50,
            "min_support": 3,
            "max_length": 2,
            "change_method": "threshold_crossing",
            "sigma": null,
            "min_magnitude": 0.0,
            "min_relative_change": 0.0,
            "global_correction": true,
            "n_permutations": 5000,
            "alpha": 0.1,
            "seed": 4
          },
          "n_transactions": 5000,
          "n_patterns": 351,
          "n_change_points_total": 0,
          "n_significant": 0,
          "precision": 0.0,
          "recall": 0.0,
          "f1": 0.0,
          "tp": 0,
          "fp": 0,
          "fn": 2,
          "time_phase1_ms": 935.7865829952061,
          "time_support_series_ms": 0.0,
          "time_attribution_ms": 142.65845902264118,
          "time_total_ms": 1078.4450420178473,
          "significant_attributions": [],
          "true_positive_pairs": [],
          "false_positive_pairs": [],
          "false_negative_pairs": [
            {
              "pattern": [
                5,
                15
              ],
              "event_id": "E2"
            },
            {
              "pattern": [
                5,
                15
              ],
              "event_id": "E1"
            }
          ],
          "false_attribution_rate": 0.0,
          "n_falsely_attributed": 0
        }
      ],
      "avg_precision": 0.3,
      "avg_recall": 0.3,
      "avg_f1": 0.3,
      "avg_false_attribution_rate": 0.0
    }
  }
}